N4Tools/Design.py
N4Tools/__init__.py
N4Tools/terminal.py
N4Tools-1.7.1.dist-info/LICENSE
N4Tools-1.7.1.dist-info/METADATA
N4Tools-1.7.1.dist-info/WHEEL
N4Tools-1.7.1.dist-info/top_level.txt
N4Tools-1.7.1.dist-info/RECORD
