Metadata-Version: 2.1
Name: N4Tools
Version: 1.7.1
Summary: Style for linux tools.
Home-page: https://github.com/No-Name-404/N4Tools
Author: Mohamed Al-Kainai
Author-email: mohamedalkainai@gmail.com
License: UNKNOWN
Platform: UNKNOWN
Classifier: Programming Language :: Python :: 3
Classifier: Programming Language :: Python :: 3.6
Classifier: Programming Language :: Python :: 3.7
Classifier: Programming Language :: Python :: 3.8
Classifier: Programming Language :: Python :: 3.9
Classifier: License :: OSI Approved :: MIT License
Requires-Dist: pyfiglet
Requires-Dist: arabic-reshaper
Requires-Dist: python-bidi
